odoo/addons/hr_payroll_document_pymupdf/README.rst
odoo/addons/hr_payroll_document_pymupdf/__init__.py
odoo/addons/hr_payroll_document_pymupdf/__manifest__.py
odoo/addons/hr_payroll_document_pymupdf/i18n/hr_payroll_document_pymupdf.pot
odoo/addons/hr_payroll_document_pymupdf/readme/DESCRIPTION.rst
odoo/addons/hr_payroll_document_pymupdf/static/description/icon.png
odoo/addons/hr_payroll_document_pymupdf/static/description/index.html
odoo/addons/hr_payroll_document_pymupdf/tests/__init__.py
odoo/addons/hr_payroll_document_pymupdf/tests/test_broken_image.pdf
odoo/addons/hr_payroll_document_pymupdf/tests/test_payroll_management.py
odoo/addons/hr_payroll_document_pymupdf/wizards/__init__.py
odoo/addons/hr_payroll_document_pymupdf/wizards/payroll_management_wizard.py
odoo_addon_hr_payroll_document_pymupdf-16.0.1.0.1.dist-info/METADATA
odoo_addon_hr_payroll_document_pymupdf-16.0.1.0.1.dist-info/WHEEL
odoo_addon_hr_payroll_document_pymupdf-16.0.1.0.1.dist-info/top_level.txt
odoo_addon_hr_payroll_document_pymupdf-16.0.1.0.1.dist-info/RECORD
