Metadata-Version: 2.1
Name: odoo-addon-hr_payroll_document_pymupdf
Version: 16.0.1.0.1
Summary: Try harder to read a PDF payslip with PyMuPDF.
Home-page: https://github.com/OCA/payroll
Author: PyTech, Odoo Community Association (OCA)
Author-email: support@odoo-community.org
License: AGPL-3
Classifier: Programming Language :: Python
Classifier: Framework :: Odoo
Classifier: Framework :: Odoo :: 16.0
Classifier: License :: OSI Approved :: GNU Affero General Public License v3
Requires-Python: >=3.10
Requires-Dist: PyMuPDF
Requires-Dist: odoo-addon-hr-payroll-document<16.1dev,>=16.0dev
Requires-Dist: odoo<16.1dev,>=16.0a
